AUTHORS
ChangeLog
LICENSE
Readme.rst
requirements.txt
setup.cfg
setup.py
tox.ini
minepycessor.egg-info/PKG-INFO
minepycessor.egg-info/SOURCES.txt
minepycessor.egg-info/dependency_links.txt
minepycessor.egg-info/entry_points.txt
minepycessor.egg-info/not-zip-safe
minepycessor.egg-info/pbr.json
minepycessor.egg-info/requires.txt
minepycessor.egg-info/top_level.txt
minepycessor_libs/__init__.py
minepycessor_libs/auth.py
minepycessor_libs/bus.py
minepycessor_libs/logger.py
minepycessor_libs/push.py
minepycessor_yaprocessor/__init__.py
minepycessor_yaprocessor/main.py
minepycessor_yaprocessor/yaprocessor.py
minepycessor_yareceiver/__init__.py
minepycessor_yareceiver/main.py