Metadata-Version: 1.1
Name: minepycessor
Version: 0.0.6
Summary: Tool for processing payment requests at minecraft servers.
Home-page: https://github.com/FromZeus/minepycessor
Author: Daniil Trishkin
Author-email: asteroid566@gmail.com
License: UNKNOWN
Platform: UNKNOWN
Classifier: Intended Audience :: Information Technology
Classifier: Intended Audience :: System Administrators
Classifier: License :: OSI Approved :: Apache Software License
Classifier: Operating System :: POSIX :: Linux
Classifier: Programming Language :: Python
Classifier: Programming Language :: Python :: 2
Classifier: Programming Language :: Python :: 2.7
